multisig_ci/__init__.py
multisig_ci/__main__.py
multisig_ci/ci_override.py
multisig_ci/hydrate_ci_cache.py
multisig_ci/run_brownie.py
multisig_ci/safes.py
multisig_ci/sentry_wrapper.py
multisig_ci/sign.py
multisig_ci/telegram.py
multisig_ci/test_telegram.sh
multisig_ci-0.9.1.dist-info/LICENSE
multisig_ci-0.9.1.dist-info/METADATA
multisig_ci-0.9.1.dist-info/WHEEL
multisig_ci-0.9.1.dist-info/RECORD
